README.md
setup.py
osupy/__init__.py
osupy/beatmap.py
osupy/error.py
osupy/event.py
osupy/player.py
osupy/subdata.py
osupy/util.py
osupy.egg-info/PKG-INFO
osupy.egg-info/SOURCES.txt
osupy.egg-info/dependency_links.txt
osupy.egg-info/top_level.txt