Metadata-Version: 1.0
Name: osupy
Version: 0.131
Summary: osu! Python API
Home-page: https://github.com/Preta-Crowz/osupy
Author: Preta
Author-email: preta@crowz.r-e.kr
License: MIT
Keywords: osu,osupy
Platform: UNKNOWN
